{
  "$schema": "https://ui.shadcn.com/schema/registry-item.json",
  "name": "badge-link",
  "type": "registry:example",
  "registryDependencies": [
    "badge"
  ],
  "files": [
    {
      "path": "registry/new-york-v4/examples/badge-link.tsx",
      "content": "import Link from \"next/link\"\n\nimport { badgeVariants } from \"@/registry/new-york-v4/ui/badge\"\n\nexport default function BadgeLinkDemo() {\n  return (\n    <div className=\"flex flex-wrap gap-2\">\n      <Link href=\"#\" className={badgeVariants({ variant: \"default\" })}>\n        Default Link\n      </Link>\n      <Link href=\"#\" className={badgeVariants({ variant: \"secondary\" })}>\n        Secondary Link\n      </Link>\n      <Link href=\"#\" className={badgeVariants({ variant: \"outline\" })}>\n        Outline Link\n      </Link>\n      <Link href=\"#\" className={badgeVariants({ variant: \"destructive\" })}>\n        Destructive Link\n      </Link>\n    </div>\n  )\n}\n",
      "type": "registry:example"
    }
  ]
}