{
  "$schema": "https://ui.shadcn.com/schema/registry-item.json",
  "name": "date-field-granularity",
  "type": "registry:example",
  "dependencies": [
    "@internationalized/date"
  ],
  "registryDependencies": [
    "date-field"
  ],
  "files": [
    {
      "path": "registry/new-york-v4/examples/date-field-granularity.tsx",
      "content": "import { DateField } from \"@/registry/new-york-v4/ui/date-field\"\n\nexport default function DateFieldGranularity() {\n  return (\n    <div className=\"space-y-4\">\n      <DateField\n        label=\"Date only\"\n        description=\"Year, month, and day.\"\n        granularity=\"day\"\n      />\n      <DateField\n        label=\"Month and year\"\n        description=\"Month and year only.\"\n        granularity=\"month\"\n      />\n    </div>\n  )\n}\n",
      "type": "registry:example"
    }
  ]
}